{
  "timestamp": "2026-05-14T04:12:50.748Z",
  "elapsedSec": 142.255,
  "burners": {
    "alice": {
      "address": "0x9817B2A24a79084505a27528eA3cEd94a659FEc0",
      "privateKey": "0xb5431a7a978616bb96b95840d2f4c7cd0fa91d6249590f876dfae9e92c7a683a"
    },
    "bob": {
      "address": "0xf43DeF37E382b87355000D8ee203B5AFa818128c",
      "privateKey": "0x71b22c1cfac114e600c2e92195b5c2c3ac87e8e1866cf7024a71dcfd328a820c"
    },
    "carol": {
      "address": "0xf1dc7AD4e4F446C4c09CBcFc4cBAaA6C3aC282A0",
      "privateKey": "0xd5e4f58bac34ede4deb00ac3908ceea97597f77411176dc8bc32ef65514bcf32"
    }
  },
  "checks": [
    {
      "action": "mint tx status",
      "pass": true,
      "detail": "tx 0x79e9b586df7d99b2750eb46d74f197b4a8974e623ae30469e4913cce67ddbce0"
    },
    {
      "action": "PassportMinted event emitted",
      "pass": true,
      "detail": "tokenId=10 owner=0x9817B2A24a79084505a27528eA3cEd94a659FEc0"
    },
    {
      "action": "event.owner == alice",
      "pass": true,
      "detail": "0x9817B2A24a79084505a27528eA3cEd94a659FEc0"
    },
    {
      "action": "event.metadataRoot == provided",
      "pass": true,
      "detail": ""
    },
    {
      "action": "passportOf(alice) > 0",
      "pass": true,
      "detail": "tokenId=10"
    },
    {
      "action": "agent.metadataRoot stored correctly",
      "pass": true,
      "detail": ""
    },
    {
      "action": "agent.trustScore initial = 0",
      "pass": true,
      "detail": "trustScore=0"
    },
    {
      "action": "agent.receiptCount initial = 0",
      "pass": true,
      "detail": "receiptCount=0"
    },
    {
      "action": "publishVersion tx status",
      "pass": true,
      "detail": "tx 0x8406696722a72fdf5057f26ee6324d11f610f3116d479e488719b87ec34b3ece"
    },
    {
      "action": "SkillPublished event emitted",
      "pass": true,
      "detail": "skill=0x3d6798927138..."
    },
    {
      "action": "event.creator == alice",
      "pass": true,
      "detail": ""
    },
    {
      "action": "event.versionId matches",
      "pass": true,
      "detail": ""
    },
    {
      "action": "event.manifestHash matches",
      "pass": true,
      "detail": ""
    },
    {
      "action": "ownerOf(skillId) == alice",
      "pass": true,
      "detail": "0x9817B2A24a79084505a27528eA3cEd94a659FEc0"
    },
    {
      "action": "versionCount == 1",
      "pass": true,
      "detail": "count=1"
    },
    {
      "action": "setPrice tx status",
      "pass": true,
      "detail": "tx 0xf03afca6e0cf393360216315d6b5c49c22feba6b50013370b4084e2b8a50f6d6"
    },
    {
      "action": "PriceUpdated event emitted",
      "pass": true,
      "detail": ""
    },
    {
      "action": "event.priceWei matches",
      "pass": true,
      "detail": "priceWei=0.005 OG"
    },
    {
      "action": "event.creatorBps == 9000",
      "pass": true,
      "detail": ""
    },
    {
      "action": "event.treasuryBps == 1000",
      "pass": true,
      "detail": ""
    },
    {
      "action": "getPricing.priced = true",
      "pass": true,
      "detail": "priced=true"
    },
    {
      "action": "getPricing.price matches",
      "pass": true,
      "detail": "0.005 OG"
    },
    {
      "action": "paySkillRun tx status",
      "pass": true,
      "detail": "tx 0x15bd142e74c4ab3d38ecf6691053eb85800b637f6a4e5e847b85f17372bbc008"
    },
    {
      "action": "SkillRunPaid event emitted",
      "pass": true,
      "detail": ""
    },
    {
      "action": "event.payer == bob",
      "pass": true,
      "detail": ""
    },
    {
      "action": "event.creator == alice",
      "pass": true,
      "detail": ""
    },
    {
      "action": "event.creatorShare = 90% of price",
      "pass": true,
      "detail": "0.0045 OG"
    },
    {
      "action": "event.treasuryShare = 10% of price",
      "pass": true,
      "detail": "0.0005 OG"
    },
    {
      "action": "event.amount == price",
      "pass": true,
      "detail": "0.005 OG"
    },
    {
      "action": "alice creatorBalance delta == 90%",
      "pass": true,
      "detail": "+0.0045 OG"
    },
    {
      "action": "treasury delta == 10%",
      "pass": true,
      "detail": "+0.0005 OG"
    },
    {
      "action": "alice lifetimeEarned delta == 90%",
      "pass": true,
      "detail": ""
    },
    {
      "action": "withdrawCreator tx status",
      "pass": true,
      "detail": "tx 0xa39d940e4e0b92fe0a52fa17c970dc944ba0578e55491b5b06ae4f306926d7ee"
    },
    {
      "action": "Withdrawn event emitted",
      "pass": true,
      "detail": ""
    },
    {
      "action": "event.amount == alice prior balance",
      "pass": true,
      "detail": "0.0045 OG"
    },
    {
      "action": "event.isTreasury == false (creator path)",
      "pass": true,
      "detail": "isTreasury=false"
    },
    {
      "action": "creatorBalance(alice) zeroed",
      "pass": true,
      "detail": ""
    },
    {
      "action": "alice wallet balance delta ~= earned - gas",
      "pass": true,
      "detail": "delta=0.0029 OG (expected 0.0029 OG)"
    },
    {
      "action": "unsetPrice tx status",
      "pass": true,
      "detail": "tx 0xbfe34c2cc66813001d49650990cb1676b65d27c69c0e7bfcf12655f6cc222112"
    },
    {
      "action": "PriceUnset event emitted",
      "pass": true,
      "detail": ""
    },
    {
      "action": "getPricing.priced = false after unset",
      "pass": true,
      "detail": "priced=false"
    },
    {
      "action": "getPricing.price = 0 after unset",
      "pass": true,
      "detail": "price=0.0"
    },
    {
      "action": "issueGrant tx status",
      "pass": true,
      "detail": "tx 0xde59ec8679f3a410ab44f2745df678c0df92477d5fd3f866e5419f8ee5c2bccb"
    },
    {
      "action": "GrantIssued event emitted",
      "pass": true,
      "detail": ""
    },
    {
      "action": "event.owner == alice",
      "pass": true,
      "detail": ""
    },
    {
      "action": "event.grantee == carol",
      "pass": true,
      "detail": ""
    },
    {
      "action": "event.scopeHash matches",
      "pass": true,
      "detail": ""
    },
    {
      "action": "isValid = true before revoke",
      "pass": true,
      "detail": ""
    },
    {
      "action": "revokeGrant tx status",
      "pass": true,
      "detail": "tx 0x329dc030336a4963086d5e2e7270906b75e31e3736347257c8f5ac3e7d5217de"
    },
    {
      "action": "GrantRevoked event emitted",
      "pass": true,
      "detail": ""
    },
    {
      "action": "event.grantId matches",
      "pass": true,
      "detail": ""
    },
    {
      "action": "isValid = false after revoke",
      "pass": true,
      "detail": ""
    }
  ],
  "summary": {
    "pass": 52,
    "fail": 0,
    "total": 52
  }
}